dma/__init__.py
dma-1.0.8.dist-info/METADATA
dma-1.0.8.dist-info/WHEEL
dma-1.0.8.dist-info/top_level.txt
dma-1.0.8.dist-info/RECORD
