Metadata-Version: 2.1
Name: dma
Version: 1.0.8
Summary: This Module Returns ASCII Art & Text in Many Different Variations Depending on The Called Function.
Home-page: https://github.com/vChimera/dma
Author: Anvil
Author-email: _@chimera.rip
Classifier: Programming Language :: Python :: 3
Classifier: License :: OSI Approved :: MIT License
Classifier: Operating System :: OS Independent
Requires-Python: >=3.6
